HPC_Tabu/__init__.py
HPC_Tabu/common/__init__.py
HPC_Tabu/common/neighborhood.py
HPC_Tabu/common/solution.py
HPC_Tabu/parallel/__init__.py
HPC_Tabu/parallel/parallel_tabu.py
HPC_Tabu/parallel/utils.py
HPC_Tabu/sequential/__init__.py
HPC_Tabu/sequential/tabu_search.py
HPC_Tabu/sequential/utils.py
hpc_tabu-0.2.32.dist-info/licenses/LICENSE.txt
hpc_tabu-0.2.32.dist-info/METADATA
hpc_tabu-0.2.32.dist-info/WHEEL
hpc_tabu-0.2.32.dist-info/top_level.txt
hpc_tabu-0.2.32.dist-info/RECORD
